buf/__init__.py
buf/validate/__init__.py
buf/validate/validate_pb2.py
buf/validate/validate_pb2.pyi
buf/validate/validate_pb2_grpc.py
flyteidl2/__init__.py
flyteidl2/app/__init__.py
flyteidl2/app/app_definition_pb2.py
flyteidl2/app/app_definition_pb2.pyi
flyteidl2/app/app_definition_pb2_grpc.py
flyteidl2/app/app_logs_payload_pb2.py
flyteidl2/app/app_logs_payload_pb2.pyi
flyteidl2/app/app_logs_payload_pb2_grpc.py
flyteidl2/app/app_logs_service_pb2.py
flyteidl2/app/app_logs_service_pb2.pyi
flyteidl2/app/app_logs_service_pb2_grpc.py
flyteidl2/app/app_payload_pb2.py
flyteidl2/app/app_payload_pb2.pyi
flyteidl2/app/app_payload_pb2_grpc.py
flyteidl2/app/app_service_pb2.py
flyteidl2/app/app_service_pb2.pyi
flyteidl2/app/app_service_pb2_grpc.py
flyteidl2/app/replica_definition_pb2.py
flyteidl2/app/replica_definition_pb2.pyi
flyteidl2/app/replica_definition_pb2_grpc.py
flyteidl2/cacheservice/__init__.py
flyteidl2/cacheservice/cacheservice_pb2.py
flyteidl2/cacheservice/cacheservice_pb2.pyi
flyteidl2/cacheservice/cacheservice_pb2_grpc.py
flyteidl2/cacheservice/v2/__init__.py
flyteidl2/cacheservice/v2/cacheservice_pb2.py
flyteidl2/cacheservice/v2/cacheservice_pb2.pyi
flyteidl2/cacheservice/v2/cacheservice_pb2_grpc.py
flyteidl2/common/__init__.py
flyteidl2/common/authorization_pb2.py
flyteidl2/common/authorization_pb2.pyi
flyteidl2/common/authorization_pb2_grpc.py
flyteidl2/common/configuration_pb2.py
flyteidl2/common/configuration_pb2.pyi
flyteidl2/common/configuration_pb2_grpc.py
flyteidl2/common/identifier_pb2.py
flyteidl2/common/identifier_pb2.pyi
flyteidl2/common/identifier_pb2_grpc.py
flyteidl2/common/identity_pb2.py
flyteidl2/common/identity_pb2.pyi
flyteidl2/common/identity_pb2_grpc.py
flyteidl2/common/list_pb2.py
flyteidl2/common/list_pb2.pyi
flyteidl2/common/list_pb2_grpc.py
flyteidl2/common/phase_pb2.py
flyteidl2/common/phase_pb2.pyi
flyteidl2/common/phase_pb2_grpc.py
flyteidl2/common/policy_pb2.py
flyteidl2/common/policy_pb2.pyi
flyteidl2/common/policy_pb2_grpc.py
flyteidl2-2.0.0.dist-info/METADATA
flyteidl2-2.0.0.dist-info/WHEEL
flyteidl2-2.0.0.dist-info/top_level.txt
flyteidl2-2.0.0.dist-info/RECORD
